{
  "generated_at": "2026-07-18 06:58:10",
  "matching_method": "weight_rule + load_cross_check",
  "summary": {
    "vehicle_count": 22,
    "match_count": 9,
    "mismatch_count": 13,
    "match_rate": 40.9,
    "confidence_distribution": {
      "高": 22,
      "中": 0,
      "低": 0
    },
    "declared_distribution": {
      "五吨车型": 6,
      "三吨车型": 14,
      "八吨车型": 2
    },
    "calibrated_distribution": {
      "五吨车型": 19,
      "三吨车型": 3
    }
  },
  "mismatches": [
    {
      "plate": "湘FA9847",
      "declared": "三吨车型",
      "avg_kg": 5109.5,
      "trips": 112,
      "total_kg": 572260.0,
      "calibrated": "五吨车型",
      "match": false,
      "confidence": "高",
      "in_expected_band": true,
      "suggestion": "自重判定「三吨车型」× 载重识别「五吨车型」：平均载重落入不同档位（载重特征提示）"
    },
    {
      "plate": "湘FB0388",
      "declared": "三吨车型",
      "avg_kg": 5003.0,
      "trips": 56,
      "total_kg": 280170.0,
      "calibrated": "五吨车型",
      "match": false,
      "confidence": "高",
      "in_expected_band": true,
      "suggestion": "自重判定「三吨车型」× 载重识别「五吨车型」：平均载重落入不同档位（载重特征提示）"
    },
    {
      "plate": "湘FA8040",
      "declared": "八吨车型",
      "avg_kg": 4966.3,
      "trips": 104,
      "total_kg": 516492.0,
      "calibrated": "五吨车型",
      "match": false,
      "confidence": "高",
      "in_expected_band": true,
      "suggestion": "自重判定「八吨车型」× 载重识别「五吨车型」：平均载重落入不同档位（载重特征提示）"
    },
    {
      "plate": "湘FB3975",
      "declared": "三吨车型",
      "avg_kg": 4891.1,
      "trips": 47,
      "total_kg": 229880.0,
      "calibrated": "五吨车型",
      "match": false,
      "confidence": "高",
      "in_expected_band": true,
      "suggestion": "自重判定「三吨车型」× 载重识别「五吨车型」：平均载重落入不同档位（载重特征提示）"
    },
    {
      "plate": "湘FB6266",
      "declared": "三吨车型",
      "avg_kg": 4849.8,
      "trips": 110,
      "total_kg": 533480.0,
      "calibrated": "五吨车型",
      "match": false,
      "confidence": "高",
      "in_expected_band": true,
      "suggestion": "自重判定「三吨车型」× 载重识别「五吨车型」：平均载重落入不同档位（载重特征提示）"
    },
    {
      "plate": "湘FB0252",
      "declared": "三吨车型",
      "avg_kg": 4803.4,
      "trips": 130,
      "total_kg": 624440.0,
      "calibrated": "五吨车型",
      "match": false,
      "confidence": "高",
      "in_expected_band": true,
      "suggestion": "自重判定「三吨车型」× 载重识别「五吨车型」：平均载重落入不同档位（载重特征提示）"
    },
    {
      "plate": "湘FC3710",
      "declared": "三吨车型",
      "avg_kg": 4627.1,
      "trips": 59,
      "total_kg": 273000.0,
      "calibrated": "五吨车型",
      "match": false,
      "confidence": "高",
      "in_expected_band": true,
      "suggestion": "自重判定「三吨车型」× 载重识别「五吨车型」：平均载重落入不同档位（载重特征提示）"
    },
    {
      "plate": "湘FA3040",
      "declared": "八吨车型",
      "avg_kg": 4584.2,
      "trips": 136,
      "total_kg": 623450.0,
      "calibrated": "五吨车型",
      "match": false,
      "confidence": "高",
      "in_expected_band": true,
      "suggestion": "自重判定「八吨车型」× 载重识别「五吨车型」：平均载重落入不同档位（载重特征提示）"
    },
    {
      "plate": "湘FC1673",
      "declared": "三吨车型",
      "avg_kg": 4419.9,
      "trips": 118,
      "total_kg": 521550.0,
      "calibrated": "五吨车型",
      "match": false,
      "confidence": "高",
      "in_expected_band": true,
      "suggestion": "自重判定「三吨车型」× 载重识别「五吨车型」：平均载重落入不同档位（载重特征提示）"
    },
    {
      "plate": "湘FB9498",
      "declared": "三吨车型",
      "avg_kg": 4412.7,
      "trips": 133,
      "total_kg": 586885.0,
      "calibrated": "五吨车型",
      "match": false,
      "confidence": "高",
      "in_expected_band": true,
      "suggestion": "自重判定「三吨车型」× 载重识别「五吨车型」：平均载重落入不同档位（载重特征提示）"
    },
    {
      "plate": "湘F86680",
      "declared": "三吨车型",
      "avg_kg": 4078.7,
      "trips": 134,
      "total_kg": 546546.0,
      "calibrated": "五吨车型",
      "match": false,
      "confidence": "高",
      "in_expected_band": true,
      "suggestion": "自重判定「三吨车型」× 载重识别「五吨车型」：平均载重落入不同档位（载重特征提示）"
    },
    {
      "plate": "湘FB2060",
      "declared": "三吨车型",
      "avg_kg": 3957.4,
      "trips": 95,
      "total_kg": 375950.0,
      "calibrated": "五吨车型",
      "match": false,
      "confidence": "高",
      "in_expected_band": true,
      "suggestion": "自重判定「三吨车型」× 载重识别「五吨车型」：平均载重落入不同档位（载重特征提示）"
    },
    {
      "plate": "湘FB7351",
      "declared": "三吨车型",
      "avg_kg": 3931.9,
      "trips": 62,
      "total_kg": 243780.0,
      "calibrated": "五吨车型",
      "match": false,
      "confidence": "高",
      "in_expected_band": true,
      "suggestion": "自重判定「三吨车型」× 载重识别「五吨车型」：平均载重落入不同档位（载重特征提示）"
    }
  ],
  "vehicles": [
    {
      "plate": "湘FC5523",
      "declared": "五吨车型",
      "avg_kg": 6370.6,
      "trips": 101,
      "total_kg": 643430.0,
      "calibrated": "五吨车型",
      "match": true,
      "confidence": "高",
      "in_expected_band": true,
      "suggestion": ""
    },
    {
      "plate": "湘FC8698",
      "declared": "五吨车型",
      "avg_kg": 6245.8,
      "trips": 53,
      "total_kg": 331030.0,
      "calibrated": "五吨车型",
      "match": true,
      "confidence": "高",
      "in_expected_band": true,
      "suggestion": ""
    },
    {
      "plate": "湘FB9409",
      "declared": "五吨车型",
      "avg_kg": 5798.9,
      "trips": 9,
      "total_kg": 52190.0,
      "calibrated": "五吨车型",
      "match": true,
      "confidence": "高",
      "in_expected_band": true,
      "suggestion": ""
    },
    {
      "plate": "湘FA8342",
      "declared": "五吨车型",
      "avg_kg": 5755.8,
      "trips": 50,
      "total_kg": 287790.0,
      "calibrated": "五吨车型",
      "match": true,
      "confidence": "高",
      "in_expected_band": true,
      "suggestion": ""
    },
    {
      "plate": "湘FA9847",
      "declared": "三吨车型",
      "avg_kg": 5109.5,
      "trips": 112,
      "total_kg": 572260.0,
      "calibrated": "五吨车型",
      "match": false,
      "confidence": "高",
      "in_expected_band": true,
      "suggestion": "自重判定「三吨车型」× 载重识别「五吨车型」：平均载重落入不同档位（载重特征提示）"
    },
    {
      "plate": "湘FB0388",
      "declared": "三吨车型",
      "avg_kg": 5003.0,
      "trips": 56,
      "total_kg": 280170.0,
      "calibrated": "五吨车型",
      "match": false,
      "confidence": "高",
      "in_expected_band": true,
      "suggestion": "自重判定「三吨车型」× 载重识别「五吨车型」：平均载重落入不同档位（载重特征提示）"
    },
    {
      "plate": "湘FA8040",
      "declared": "八吨车型",
      "avg_kg": 4966.3,
      "trips": 104,
      "total_kg": 516492.0,
      "calibrated": "五吨车型",
      "match": false,
      "confidence": "高",
      "in_expected_band": true,
      "suggestion": "自重判定「八吨车型」× 载重识别「五吨车型」：平均载重落入不同档位（载重特征提示）"
    },
    {
      "plate": "湘FB3975",
      "declared": "三吨车型",
      "avg_kg": 4891.1,
      "trips": 47,
      "total_kg": 229880.0,
      "calibrated": "五吨车型",
      "match": false,
      "confidence": "高",
      "in_expected_band": true,
      "suggestion": "自重判定「三吨车型」× 载重识别「五吨车型」：平均载重落入不同档位（载重特征提示）"
    },
    {
      "plate": "湘FB6266",
      "declared": "三吨车型",
      "avg_kg": 4849.8,
      "trips": 110,
      "total_kg": 533480.0,
      "calibrated": "五吨车型",
      "match": false,
      "confidence": "高",
      "in_expected_band": true,
      "suggestion": "自重判定「三吨车型」× 载重识别「五吨车型」：平均载重落入不同档位（载重特征提示）"
    },
    {
      "plate": "湘FB0252",
      "declared": "三吨车型",
      "avg_kg": 4803.4,
      "trips": 130,
      "total_kg": 624440.0,
      "calibrated": "五吨车型",
      "match": false,
      "confidence": "高",
      "in_expected_band": true,
      "suggestion": "自重判定「三吨车型」× 载重识别「五吨车型」：平均载重落入不同档位（载重特征提示）"
    },
    {
      "plate": "湘FA8347",
      "declared": "五吨车型",
      "avg_kg": 4651.7,
      "trips": 99,
      "total_kg": 460520.0,
      "calibrated": "五吨车型",
      "match": true,
      "confidence": "高",
      "in_expected_band": true,
      "suggestion": ""
    },
    {
      "plate": "湘FC3710",
      "declared": "三吨车型",
      "avg_kg": 4627.1,
      "trips": 59,
      "total_kg": 273000.0,
      "calibrated": "五吨车型",
      "match": false,
      "confidence": "高",
      "in_expected_band": true,
      "suggestion": "自重判定「三吨车型」× 载重识别「五吨车型」：平均载重落入不同档位（载重特征提示）"
    },
    {
      "plate": "湘FA3040",
      "declared": "八吨车型",
      "avg_kg": 4584.2,
      "trips": 136,
      "total_kg": 623450.0,
      "calibrated": "五吨车型",
      "match": false,
      "confidence": "高",
      "in_expected_band": true,
      "suggestion": "自重判定「八吨车型」× 载重识别「五吨车型」：平均载重落入不同档位（载重特征提示）"
    },
    {
      "plate": "湘FC1673",
      "declared": "三吨车型",
      "avg_kg": 4419.9,
      "trips": 118,
      "total_kg": 521550.0,
      "calibrated": "五吨车型",
      "match": false,
      "confidence": "高",
      "in_expected_band": true,
      "suggestion": "自重判定「三吨车型」× 载重识别「五吨车型」：平均载重落入不同档位（载重特征提示）"
    },
    {
      "plate": "湘FB9498",
      "declared": "三吨车型",
      "avg_kg": 4412.7,
      "trips": 133,
      "total_kg": 586885.0,
      "calibrated": "五吨车型",
      "match": false,
      "confidence": "高",
      "in_expected_band": true,
      "suggestion": "自重判定「三吨车型」× 载重识别「五吨车型」：平均载重落入不同档位（载重特征提示）"
    },
    {
      "plate": "湘F86680",
      "declared": "三吨车型",
      "avg_kg": 4078.7,
      "trips": 134,
      "total_kg": 546546.0,
      "calibrated": "五吨车型",
      "match": false,
      "confidence": "高",
      "in_expected_band": true,
      "suggestion": "自重判定「三吨车型」× 载重识别「五吨车型」：平均载重落入不同档位（载重特征提示）"
    },
    {
      "plate": "湘FB2060",
      "declared": "三吨车型",
      "avg_kg": 3957.4,
      "trips": 95,
      "total_kg": 375950.0,
      "calibrated": "五吨车型",
      "match": false,
      "confidence": "高",
      "in_expected_band": true,
      "suggestion": "自重判定「三吨车型」× 载重识别「五吨车型」：平均载重落入不同档位（载重特征提示）"
    },
    {
      "plate": "湘FB7351",
      "declared": "三吨车型",
      "avg_kg": 3931.9,
      "trips": 62,
      "total_kg": 243780.0,
      "calibrated": "五吨车型",
      "match": false,
      "confidence": "高",
      "in_expected_band": true,
      "suggestion": "自重判定「三吨车型」× 载重识别「五吨车型」：平均载重落入不同档位（载重特征提示）"
    },
    {
      "plate": "湘FB8611",
      "declared": "五吨车型",
      "avg_kg": 3917.2,
      "trips": 116,
      "total_kg": 454400.0,
      "calibrated": "五吨车型",
      "match": true,
      "confidence": "高",
      "in_expected_band": true,
      "suggestion": ""
    },
    {
      "plate": "湘FA8340",
      "declared": "三吨车型",
      "avg_kg": 3343.6,
      "trips": 70,
      "total_kg": 234050.0,
      "calibrated": "三吨车型",
      "match": true,
      "confidence": "高",
      "in_expected_band": true,
      "suggestion": ""
    },
    {
      "plate": "湘FA5403",
      "declared": "三吨车型",
      "avg_kg": 3308.7,
      "trips": 47,
      "total_kg": 155510.0,
      "calibrated": "三吨车型",
      "match": true,
      "confidence": "高",
      "in_expected_band": true,
      "suggestion": ""
    },
    {
      "plate": "湘FB9046",
      "declared": "三吨车型",
      "avg_kg": 3155.5,
      "trips": 76,
      "total_kg": 239820.0,
      "calibrated": "三吨车型",
      "match": true,
      "confidence": "高",
      "in_expected_band": true,
      "suggestion": ""
    }
  ]
}